rustc_t_x64_win_msvc/__init__.py
rustc_t_x64_win_msvc/data/libicu_list-6344a36af7ea4589.rmeta
rustc_t_x64_win_msvc/data/librand_chacha-b1f7e7af7590eb00.rmeta
rustc_t_x64_win_msvc/data/libregex_syntax-83f2eab5165ac334.rmeta
rustc_t_x64_win_msvc/data/librustc_baked_icu_data-e6d2a1669edac8ee.rmeta
rustc_t_x64_win_msvc/data/librustc_codegen_ssa-9abe15cb0d7a2822.rmeta
rustc_t_x64_win_msvc/data/librustc_feature-9d85e9714067370f.rmeta
rustc_t_x64_win_msvc/data/librustc_metadata-529a31d0c1043d1a.rmeta
rustc_t_x64_win_msvc/data/librustc_proc_macro-e1028f846ca76020.rmeta
rustc_t_x64_win_msvc/data/librustc_ty_utils-45d351228ed77742.rmeta
rustc_t_x64_win_msvc/data/libruzstd-15996101d5808e44.rmeta
rustc_t_x64_win_msvc/data/libscoped_tls-19c5675bfa6bc9bb.rmeta
rustc_t_x64_win_msvc/data/libunicode_xid-99e1e30f3faa8231.rmeta
rustc_t_x64_win_msvc/data/unic_langid_macros_impl-d421a4d1928e2e5c.dll
rustc_t_x64_win_msvc/data/windows_implement-24688cbe58033ffc.dll.lib
rustc_t_x64_win_msvc/data/windows_interface-fa61fe6bfcbc4a3d.dll.lib
rustc_t_x64_win_msvc-1.91.0.post8.dist-info/METADATA
rustc_t_x64_win_msvc-1.91.0.post8.dist-info/WHEEL
rustc_t_x64_win_msvc-1.91.0.post8.dist-info/top_level.txt
rustc_t_x64_win_msvc-1.91.0.post8.dist-info/RECORD
