Metadata-Version: 2.4
Name: rustc_t_x64_win_msvc
Version: 1.91.0.post8
Summary: Segment rustc-dev.target.x86_64-pc-windows-msvc part p8
License-Expression: MIT
